db2mermaid/__init__.py
db2mermaid/db2mermaid.py
DB2mermaid-1.0.3.dist-info/METADATA
DB2mermaid-1.0.3.dist-info/WHEEL
DB2mermaid-1.0.3.dist-info/top_level.txt
DB2mermaid-1.0.3.dist-info/RECORD
