Metadata-Version: 2.1
Name: DB2mermaid
Version: 1.0.3
Summary: db -> mermaid ER code
Home-page: https://github.com/kitsystemyou/make-mermaid-swim-by-db
Author: singsignalyou
Author-email: kitsystemyou@gmail.com
License: MIT
Keywords: mermaid erDiagram
Classifier: License :: OSI Approved :: MIT License
Classifier: Programming Language :: Python :: 3.10
Requires-Dist: sqlalchemy
Requires-Dist: mysqlclient
